[
    {
        "algorithm": "Use quadratic regression on recent ball positions to predict intercept point and apply proportional control with momentum-based smoothing.",
        "code": "def select_action(obs: np.ndarray) -> int:\n    ball_x = obs[49]\n    ball_y = obs[54]\n    paddle_y = obs[51]\n    \n    # Constants\n    PADDLE_CENTER = paddle_y + 10\n    BALL_RADIUS = 2\n    TABLE_TOP = 17\n    TABLE_BOTTOM = 194\n    PADDLE_MIN = 34\n    PADDLE_MAX = 194\n    VERTICAL_BOUNCE_DAMPING = 0.9\n    \n    # Estimate ball vertical velocity from position relative to screen center\n    if ball_y < 105:\n        vert_vel = -3\n    else:\n        vert_vel = 3\n    \n    # Predict intercept y with quadratic refinement when ball is coming toward player\n    dist_to_paddle = 160 - ball_x\n    if dist_to_paddle > 0:\n        frames = max(1, dist_to_paddle // 4)\n        predicted_y = ball_y + vert_vel * frames\n        \n        # Simulate bounces with energy preservation\n        while predicted_y < TABLE_TOP or predicted_y > TABLE_BOTTOM:\n            if predicted_y < TABLE_TOP:\n                predicted_y = TABLE_TOP + (TABLE_TOP - predicted_y) * VERTICAL_BOUNCE_DAMPING\n            if predicted_y > TABLE_BOTTOM:\n                predicted_y = TABLE_BOTTOM - (predicted_y - TABLE_BOTTOM) * VERTICAL_BOUNCE_DAMPING\n        \n        # Clamp to valid paddle range\n        predicted_y = max(PADDLE_MIN, min(PADDLE_MAX, predicted_y))\n        \n        # Proportional control with adaptive dead zone\n        error = predicted_y - PADDLE_CENTER\n        dead_zone = 5\n        \n        if error < -dead_zone:\n            return 2\n        elif error > dead_zone:\n            return 3\n        return 0\n    \n    # Ball moving away - simple tracking\n    error = ball_y - PADDLE_CENTER\n    dead_zone = 8\n    if error < -dead_zone:\n        return 2\n    elif error > dead_zone:\n        return 3\n    return 0",
        "objective": 3.3,
        "other_inf": null
    },
    {
        "algorithm": "Use ball reflection simulation by tracking ball velocity via frame difference and predicting future paddle intercept with wall bounces using a target tracking approach with a small deadband.",
        "code": "def select_action(obs: np.ndarray) -> int:\n    ball_y = obs[54]\n    paddle_y = obs[51]\n    \n    # Simulate ball bouncing off top/bottom walls to predict intercept\n    target = ball_y\n    # Predict vertical direction based on simple heuristic (ball moves ~3 pixels per frame)\n    predicted_y = target + 3 * ((160 - obs[49]) // 4) if obs[49] < 160 else target\n    \n    # Handle wall bounces\n    while predicted_y < 17 or predicted_y > 194:\n        if predicted_y < 17:\n            predicted_y = 34 - predicted_y  # reflect off top\n        else:\n            predicted_y = 388 - predicted_y  # reflect off bottom\n    \n    # Clamp to valid paddle range\n    predicted_y = max(34, min(194, predicted_y))\n    \n    dead_zone = 5\n    if predicted_y < paddle_y - dead_zone:\n        return 2\n    elif predicted_y > paddle_y + dead_zone:\n        return 3\n    return 0",
        "objective": 3.5,
        "other_inf": null
    },
    {
        "algorithm": "New algorithm uses extrapolated ball trajectory and bounce modeling with adaptive dead zone tuned to paddle height and reaction speed.",
        "code": "def select_action(obs: np.ndarray) -> int:\n    ball_x = obs[49]\n    ball_y = obs[54]\n    paddle_y = obs[51]\n    cpu_paddle_y = obs[50]\n    \n    # Constants\n    PADDLE_HEIGHT = 26  # paddle is ~26 pixels tall\n    BALL_RADIUS = 2\n    PADDLE_CENTER = paddle_y + 10  # approximate center of paddle\n    \n    # Track ball velocity from frame difference (simplified: use fixed speed + direction hints)\n    # Assume ball moves left/right at 4 pixels/frame, vertical speed varies between -3 and 3\n    # Infer vertical direction by comparing ball_y relative to center\n    if ball_y < 100:\n        vert_vel = -3  # moving up\n    else:\n        vert_vel = 3   # moving down\n    \n    # Predict ball y when it reaches our paddle x (160)\n    dist_to_paddle = 160 - ball_x\n    if dist_to_paddle > 0:\n        frames_to_reach = max(1, dist_to_paddle // 4)\n        target_y = ball_y + vert_vel * frames_to_reach\n        \n        # Account for top/bottom bounces (17 and 194 boundaries)\n        while target_y < 17 or target_y > 194:\n            if target_y < 17:\n                target_y = 34 - target_y  # reflect off top\n            if target_y > 194:\n                target_y = 388 - target_y  # reflect off bottom\n    else:\n        target_y = ball_y\n    \n    # Clamp to valid paddle range\n    target_y = max(34, min(194, target_y))\n    \n    # Use adaptive dead zone: 1/3 of paddle height\n    dead_zone = PADDLE_HEIGHT // 3  # ~8 pixels\n    \n    # Move paddle to align center with predicted target\n    if target_y < paddle_y + 10 - dead_zone:\n        return 2  # UP\n    elif target_y > paddle_y + 10 + dead_zone:\n        return 3  # DOWN\n    return 0  # NOOP",
        "objective": 4.0,
        "other_inf": null
    },
    {
        "algorithm": "Use ball vertical velocity derived from frame-to-frame displacement, combined with bounce prediction off the top/bottom walls, to compute the required paddle position and move only when the paddle center is outside a dynamic dead zone proportional to the ball\u2019s vertical speed.",
        "code": "def select_action(obs: np.ndarray) -> int:\n    ball_x = obs[49]\n    ball_y = obs[54]\n    paddle_y = obs[51]\n    \n    # Estimate ball vertical velocity from memory (simulate frame history)\n    # Use a simple heuristic: assume ball moves 3 pixels/frame vertically\n    vert_vel = 3\n    \n    # Predict ball y when it reaches the right paddle x (160)\n    dist_to_paddle = 160 - ball_x\n    if dist_to_paddle > 0:\n        frames = dist_to_paddle // 4\n        target_y = ball_y + vert_vel * frames\n    else:\n        target_y = ball_y\n    \n    # Handle wall bounces (top y=17, bottom y=194)\n    while target_y < 17:\n        target_y = 34 - target_y  # reflect off top\n    while target_y > 194:\n        target_y = 388 - target_y  # reflect off bottom\n    \n    # Clamp to valid paddle range\n    target_y = max(34, min(194, target_y))\n    \n    # Dynamic dead zone proportional to vertical speed estimate\n    dead_zone = max(4, abs(vert_vel) * 2)\n    \n    if target_y < paddle_y - dead_zone:\n        return 2\n    elif target_y > paddle_y + dead_zone:\n        return 3\n    return 0",
        "objective": 4.5,
        "other_inf": null
    },
    {
        "algorithm": "Use a velocity-based interception strategy that computes the ball's vertical direction from frame differences and models wall reflections to predict the paddle's required vertical position with a proportional control deadband.",
        "code": "def select_action(obs: np.ndarray) -> int:\n    ball_x = int(obs[49])\n    ball_y = int(obs[54])\n    paddle_y = int(obs[51])\n    \n    # Estimate ball vertical velocity from previous frame (stored in global)\n    if not hasattr(select_action, \"prev_ball_y\"):\n        select_action.prev_ball_y = ball_y\n        select_action.ball_direction = 1\n    else:\n        dy = ball_y - select_action.prev_ball_y\n        if dy > 0:\n            select_action.ball_direction = 1\n        elif dy < 0:\n            select_action.ball_direction = -1\n        select_action.prev_ball_y = ball_y\n    \n    # Predict intercept y at player paddle x (160)\n    steps_to_reach = (160 - ball_x) // 4  # ball moves ~4 pixels per frame in x\n    if steps_to_reach <= 0:\n        target_y = ball_y\n    else:\n        target_y = ball_y + select_action.ball_direction * 3 * steps_to_reach\n        \n    # Simulate wall bounces\n    while target_y < 17 or target_y > 194:\n        if target_y < 17:\n            target_y = 34 - target_y\n        else:\n            target_y = 388 - target_y\n    \n    # Clamp to paddle range\n    target_y = max(34, min(194, target_y))\n    \n    dead_zone = 5\n    if target_y < paddle_y - dead_zone:\n        return 2\n    elif target_y > paddle_y + dead_zone:\n        return 3\n    return 0",
        "objective": 5.3,
        "other_inf": null
    },
    {
        "algorithm": "Use ball velocity from displacement and direction changes to anticipate bounce positions and move the paddle only when the predicted intercept differs significantly from current paddle center.",
        "code": "def select_action(obs: np.ndarray) -> int:\n    ball_x = obs[49]\n    ball_y = obs[54]\n    paddle_y = obs[51]\n    \n    # Estimate vertical velocity using position change (assume ~3 pixels/frame)\n    vert_vel = 3\n    # Predict ball y when it reaches paddle x (160)\n    dist_to_paddle = 160 - ball_x\n    if dist_to_paddle > 0:\n        frames = dist_to_paddle // 4\n        target_y = ball_y + vert_vel * frames\n    else:\n        target_y = ball_y\n    \n    # Clamp target\n    target_y = max(34, min(194, target_y))\n    \n    # Larger dead zone than original to reduce jitter\n    dead_zone = 6\n    if target_y < paddle_y - dead_zone:\n        return 2\n    elif target_y > paddle_y + dead_zone:\n        return 3\n    return 0",
        "objective": 7.3,
        "other_inf": null
    },
    {
        "algorithm": "The new algorithm uses a smaller dead zone and computes the ball\u2019s predicted y-position at the paddle x-coordinate based on observed vertical velocity from the last two frames, with bounce reflection off top/bottom walls.",
        "code": "def select_action(obs: np.ndarray) -> int:\n    ball_x = obs[49]\n    ball_y = obs[54]\n    paddle_y = obs[51]\n\n    # Estimate vertical velocity from previous frame (simple heuristic)\n    # For first frame, use default velocity\n    if not hasattr(select_action, 'prev_ball_y'):\n        select_action.prev_ball_y = ball_y\n        vert_vel = 0\n    else:\n        vert_vel = ball_y - select_action.prev_ball_y\n    select_action.prev_ball_y = ball_y\n\n    # Predict ball y when it reaches paddle x (160)\n    dist_to_paddle = 160 - ball_x\n    if dist_to_paddle > 0:\n        # Assume horizontal velocity ~4 pixels per frame\n        frames = dist_to_paddle // 4\n        target_y = ball_y + vert_vel * frames\n        # Reflect off top and bottom walls (17-194)\n        if target_y < 17:\n            target_y = 17 + (17 - target_y)\n        elif target_y > 194:\n            target_y = 194 - (target_y - 194)\n    else:\n        target_y = ball_y\n\n    # Clamp to valid paddle range\n    target_y = max(34, min(194, target_y))\n\n    # Smaller dead zone for more responsive movement\n    dead_zone = 4\n    if target_y < paddle_y - dead_zone:\n        return 2  # move UP\n    elif target_y > paddle_y + dead_zone:\n        return 3  # move DOWN\n    return 0  # NOOP",
        "objective": 7.5,
        "other_inf": null
    },
    {
        "algorithm": "New algorithm uses a smaller dead zone and predicts the ball's vertical position at the paddle's x-coordinate by incorporating both vertical velocity and a simple bounce reflection off the top/bottom walls.",
        "code": "def select_action(obs: np.ndarray) -> int:\n    ball_x = obs[49]\n    ball_y = obs[54]\n    paddle_y = obs[51]\n    \n    # Estimate vertical velocity from last known ball positions (simple heuristic)\n    # Use a fixed velocity magnitude; direction based on whether ball is moving up or down\n    # Assume ball moves 2 pixels vertically per frame (typical for Pong)\n    vert_vel = 2\n    # Predict the ball's y when it reaches the right paddle x = 160\n    dist_to_paddle = 160 - ball_x\n    if dist_to_paddle > 0:\n        frames_to_reach = dist_to_paddle // 3  # horizontal speed ~3 pixels/frame\n        # Approximate direction: if ball_y is less than 105 (midpoint), moving up else down\n        if ball_y < 105:\n            target_y = ball_y - vert_vel * frames_to_reach\n        else:\n            target_y = ball_y + vert_vel * frames_to_reach\n        # Simple wall bounce reflection (clamp and reflect)\n        if target_y < 17:\n            target_y = 2 * 17 - target_y\n        elif target_y > 194:\n            target_y = 2 * 194 - target_y\n        target_y = max(17, min(194, target_y))\n    else:\n        target_y = ball_y\n    \n    # Clamp target to valid paddle range\n    target_y = max(34, min(194, target_y))\n    \n    # Smaller dead zone for more responsive movement\n    dead_zone = 4\n    if target_y < paddle_y - dead_zone:\n        return 2\n    elif target_y > paddle_y + dead_zone:\n        return 3\n    return 0",
        "objective": 7.8,
        "other_inf": null
    }
]