{
    "sample_order": 26,
    "operator": "m2",
    "algorithm": "New algorithm: Uses an exponential diversification bonus that grows with tabu age and iteration progress, combined with a dynamic aspiration threshold that tightens based on recent improvement frequency, while applying a Cauchy-distributed perturbation to scores that decays over time.",
    "code": "def score_moves(delta_costs: np.ndarray, is_tabu_mask: np.ndarray,\n                best_cost: float, current_cost: float, tabu_ages: np.ndarray,\n                iteration: int, max_iterations: int) -> np.ndarray:\n    scores = np.full(len(delta_costs), -np.inf)\n    non_tabu = ~is_tabu_mask\n    progress = iteration / max_iterations\n\n    # Exponential diversification bonus for tabu moves, scaled by age and progress\n    tabu_diversification = np.where(is_tabu_mask, np.exp(tabu_ages / (max_iterations * 0.5)) * (0.5 + progress), 0.0)\n\n    # Dynamic aspiration: allow tabu move if it beats best or if improving and tabu age > threshold that decreases over time\n    aspiration_threshold = 0.4 * max_iterations * (1 - 0.5 * progress)\n    aspiration_improve = current_cost + delta_costs < best_cost\n    aspiration_tabu = (delta_costs < 0) & (tabu_ages > aspiration_threshold)\n    aspiration = is_tabu_mask & (aspiration_improve | aspiration_tabu)\n\n    # Base score: negative delta (higher for improvements) with Cauchy noise decaying over iterations\n    noise_scale = 0.5 * (1 - progress)\n    noise = np.random.standard_cauchy(len(delta_costs)) * noise_scale\n    base_score = -delta_costs + noise\n\n    # Non-tabu moves: base score\n    scores[non_tabu] = base_score[non_tabu]\n\n    # Allowed tabu moves: base score + diversification bonus\n    scores[aspiration] = base_score[aspiration] + 10.0 * tabu_diversification[aspiration]\n\n    # Early exploration: allow some worsening moves with probability based on delta magnitude\n    if progress < 0.15:\n        worsening = (delta_costs > 0) & non_tabu\n        accept_prob = np.clip(1.0 / (1.0 + delta_costs[worsening] / (current_cost + 1e-8)), 0, 0.3)\n        accept_mask = np.random.uniform(0, 1, size=worsening.sum()) < accept_prob\n        scores[worsening] = np.where(accept_mask, scores[worsening] - 0.3 * delta_costs[worsening], -np.inf)\n\n    return scores",
    "objective": 385.78278
}